{
	"version": "https://jsonfeed.org/version/1",
	"title": "Michael Descy",
	"home_page_url": "https://mjdescy.micro.blog/",
	"feed_url": "https://mjdescy.micro.blog/feed.json",
	"items": [
		
		{
			"id": "http://mjdescy.micro.blog/2018/02/02/swiftodo-is-now.html",
	      	
			"content_html": "<p><a href=\"https://itunes.apple.com/us/app/swiftodo-task-list-for-todo.txt/id1073798440?ls=1&amp;mt=8\">SwiftoDo 2.7.1 is now available in the App Store</a>. It includes minor updates and bug fixes. </p>\n",
			"date_published": "2018-02-02T14:44:00-05:00",
			"url": "https://mjdescy.micro.blog/2018/02/02/swiftodo-is-now.html"
		},
		
		{
			"id": "http://mjdescy.micro.blog/2018/02/02/based-on-my.html",
	      	
			"content_html": "<p>Based on my podcast listening for the week, I’ve concluded (and I’m being half serious here) that Amazon Alexa’s key feature, and Siri’s key shortcoming, is support for multiple named kitchen timers. That seems like an easy gap to fill. When Apple will finally ship that feature?</p>\n",
			"date_published": "2018-02-02T11:34:00-05:00",
			"url": "https://mjdescy.micro.blog/2018/02/02/based-on-my.html"
		},
		
		{
			"id": "http://mjdescy.micro.blog/2018/02/02/ive-got-a.html",
	      	
			"content_html": "<p>I’ve got a couple releases lined up for my iOS app, and need to think about a total rewrite for its macOS counterpart. So, instead of doing anything constructive tonight, I am watching “Supergirl”. Rest is good sometimes, no?</p>\n",
			"date_published": "2018-02-01T22:39:00-05:00",
			"url": "https://mjdescy.micro.blog/2018/02/01/ive-got-a.html"
		},
		
		{
			"id": "http://mjdescy.micro.blog/2018/02/01/im-thoroughly-enjoying.html",
	      	
			"content_html": "<p>I’m thoroughly enjoying Matt Birchler’s <a href=\"https://itunes.apple.com/us/playlist/homepod-testing/pl.u-qpZDJs2RG247\">“HomePod Testing” playlist</a> on Apple Music 🎵. Each track is well produced and interesting. It’s great music to work to.</p>\n\n<p><img src=\"http://mjdescy.micro.blog/uploads/2018/390bb06eb4.jpg\" width=\"600\" height=\"462\" /></p>\n",
			"date_published": "2018-02-01T11:04:00-05:00",
			"url": "https://mjdescy.micro.blog/2018/02/01/im-thoroughly-enjoying.html"
		},
		
		{
			"id": "http://mjdescy.micro.blog/2018/02/01/i-spent-my.html",
	      	
			"content_html": "<p>I spent my evening figuring out how to transfer an 18-year-old domain name and several personal websites to new hosting providers. It’s not something I do every day, so I won’t be surprised if something gets screwed up—not that it matters too much.</p>\n",
			"date_published": "2018-01-31T22:58:00-05:00",
			"url": "https://mjdescy.micro.blog/2018/01/31/i-spent-my.html"
		},
		
		{
			"id": "http://mjdescy.micro.blog/2018/01/31/the-program-i.html",
	      	
			"content_html": "<p>The program I wrote yesterday has been running, with no output whatsoever, for over 12 hours now, and is nowhere near done. So, how do you, time- and space- efficiently, search for 60,000 strings within 20 million lines of text? 😅 </p>\n",
			"date_published": "2018-01-31T08:16:00-05:00",
			"url": "https://mjdescy.micro.blog/2018/01/31/the-program-i.html"
		},
		
		{
			"id": "http://mjdescy.micro.blog/2018/01/30/it-looks-like.html",
	      	
			"content_html": "<p>It looks like I will be working overtime this week. Things are crazy. I think I am involved in getting two or three new practice lines off the ground.</p>\n",
			"date_published": "2018-01-30T17:09:00-05:00",
			"url": "https://mjdescy.micro.blog/2018/01/30/it-looks-like.html"
		},
		
		{
			"id": "http://mjdescy.micro.blog/2018/01/30/im-coding-something.html",
	      	
			"content_html": "<p>I’m coding something new for work today, mostly because ACL can’t read my enormous data files correctly all the way through.</p>\n",
			"date_published": "2018-01-30T12:58:00-05:00",
			"url": "https://mjdescy.micro.blog/2018/01/30/im-coding-something.html"
		},
		
		{
			"id": "http://mjdescy.micro.blog/2018/01/30/every-font-on.html",
	      	
			"content_html": "<p>Every font on all my devices somehow looks different to me today. What the heck happened to my eyes?</p>\n",
			"date_published": "2018-01-29T22:09:00-05:00",
			"url": "https://mjdescy.micro.blog/2018/01/29/every-font-on.html"
		},
		
		{
			"id": "http://mjdescy.micro.blog/2018/01/29/today-was-unexpectedly.html",
	      	
			"content_html": "<p>Today was unexpectedly full of proposal work for me. I think I need to help revamp how we write proposals at my firm. It was <em>so</em> hectic and we could have done better if we had more time.</p>\n",
			"date_published": "2018-01-29T18:58:00-05:00",
			"url": "https://mjdescy.micro.blog/2018/01/29/today-was-unexpectedly.html"
		}
		
	]
}
